foodreversefda/__init__.py
foodreversefda/city.py
foodreversefda/city_test.py
foodreversefda/classification.py
foodreversefda/classification_test.py
foodreversefda/date.py
foodreversefda/date_test.py
foodreversefda/event_id.py
foodreversefda/event_id_test.py
foodreversefda-0.1.8.dist-info/METADATA
foodreversefda-0.1.8.dist-info/WHEEL
foodreversefda-0.1.8.dist-info/RECORD
