Metadata-Version: 2.1
Name: foodreversefda
Version: 0.1.8
Summary: 
License: MIT
Author: Yifei Chen
Author-email: yc4307@columbia.edu
Requires-Python: >=3.10,<4.0
Classifier: License :: OSI Approved :: MIT License
Classifier: Programming Language :: Python :: 3
Classifier: Programming Language :: Python :: 3.10
Classifier: Programming Language :: Python :: 3.11
Classifier: Programming Language :: Python :: 3.12
Requires-Dist: pytest (>=7.3.1,<8.0.0)
Requires-Dist: requests (>=2.31.0,<3.0.0)
Requires-Dist: vcrpy (>=5.1.0,<6.0.0)
